openseek/__init__.py
openseek/internal/exceptions.py
openseek/internal/objects.py
openseek/internal/selectors.py
openseek/openseek.py
openseek-0.1.4.dist-info/LICENSE
openseek-0.1.4.dist-info/METADATA
openseek-0.1.4.dist-info/WHEEL
openseek-0.1.4.dist-info/RECORD
