Metadata-Version: 2.3
Name: openseek
Version: 0.1.4
Summary: OpenSeek is an open-source Python library that provides seamless, cost-free access to DeepSeek models. Designed for developers and researchers, it offers a simple and unified interface to interact with various DeepSeek LLMs without requiring API keys, subscriptions, or paid plans.
License: MIT
Keywords: openseek,llm,deep learning,chatgpt,openai,llama,transformers
Author: Daniel Cuzneţov danielcuznetov04@gmail.com
Requires-Python: >=3.10,<4.0
Classifier: Programming Language :: Python :: 3
Classifier: Programming Language :: Python :: 3.10
Classifier: Programming Language :: Python :: 3.11
Classifier: Programming Language :: Python :: 3.12
Classifier: License :: OSI Approved :: MIT License
Classifier: Operating System :: OS Independent
Classifier: Development Status :: 4 - Beta
Classifier: Intended Audience :: Developers
Classifier: Intended Audience :: Science/Research
Classifier: Natural Language :: English
Requires-Dist: beautifulsoup4 (>=4.13.3,<5.0.0)
Requires-Dist: inscriptis (>=2.6.0,<3.0.0)
Requires-Dist: pyvirtualdisplay (>=3.0,<4.0)
Requires-Dist: zendriver (>=0.5.1,<0.6.0)
